Workbook
Name _Hlk22646034: 'Budget détaillé'!#REF!

Sheet Budget détaillé
A3: Génération Sans Limites/ Youth Challenge 2019/2020
A4: BUDGET ESTIMATIF Youth Challenge Congo
A5: N⁰ | B5: Description du poste | C5: Nombre d’unités | D5: Types d’Unités | E5: Fréquence | F5: Unité de Fréquence | G5: Prix/coût unitaire | H5: Montant total | I5: Montant en USD | J5: Source de financement
I6: 590.42 | J6: GenU | K6: UNDP | L6: UNICEF
A7: Extrant 1 | B7: Sensibilisation sur le projet "Youth Challenge"
A8: Activité 1.1 | B8: Communication sur le projet (dépliants, gadgets, presse, etc.)
A9: Grp.Cibles | B9: Grand public: Décideurs, ministres, partenaires techniques et financiers…
B10: Confection des banderoles en bâche | C10: 4 | D10: Unité | E10: 1 | F10: fois | G10: 40000 | H10: =G10*E10*C10 -> 160000
B11: Déploiement banderoles (achat corde et per diem pour les manutentionnaires) | C11: 4 | D11: Unité | E11: 1 | F11: fois | G11: 2000 | H11: =G11*E11*C11 -> 8000
B12: Conception des Kakemono | C12: 2 | D12: Unité | E12: 1 | F12: fois | G12: 150000 | H12: =G12*E12*C12 -> 300000
B13: Conception des supports visuels: Affiches Dépliants | C13: 2 | D13: Produits | E13: 1 | F13: fois | G13: 100000 | H13: =G13*E13*C13 -> 200000
B14: Impression Affiches A3 | C14: 100 | D14: Exemplaires | E14: 1 | F14: tirage | G14: 1500 | H14: =G14*E14*C14 -> 150000
B15: Impression dépliants A4 | C15: 300 | D15: Exemplaires | E15: 1 | F15: Tirage | G15: 1000 | H15: =G15*E15*C15 -> 300000
B16: Diffusion d'un communiqué radio/ télévisé | C16: 1 | D16: Communiqué | E16: 5 | F16: Diffusions | G16: 20000 | H16: =G16*E16*C16 -> 100000
B17: Réseaux sociaux | C17: 1 | D17: Publication | E17: 1 | F17: Année | G17: 10000 | H17: =G17*E17*C17 -> 10000
B18: Décoration T-shirts | C18: 100 | D18: t-shirts | E18: 2 | F18: tirage | G18: 3000 | H18: =G18*E18*C18 -> 600000
B19: Décoration Polos | C19: 55 | D19: Polos | E19: 1 | F19: Impression | G19: 5000 | H19: =G19*E19*C19 -> 275000
B20: Organisation des réunions de sensibilisation | C20: 5 | D20: Réunions | E20: 1 | F20: Forfait | G20: 50000 | H20: =G20*E20*C20 -> 250000
A21: Sous-total activité 1.1: Communication sur le projet (dépliants, gadgets, presse, etc.) | H21: =SUM(H10:H20) -> 2353000 | I21: =H21/I6 -> 3985.2986 | J21: 1000 | K21: 0 | L21: =I21-J21-K21 -> 2985.2986
A22: Activité 1.2. | B22: Organisation de la cérémonie de lancement du Youth Challenge
A23: Grp.Cibles | B23: Ministères, Secteur privé,SNU, Médias , potentiels candidats
B24: Location de la salle | C24: 1 | E24: 1 | F24: Jour | G24: 150000 | H24: =C24*E24*G24 -> 150000
B25: Cocktail participants | C25: 150 | D25: Personnes | E25: 1 | F25: Jour | G25: 10000 | H25: =C25*E25*G25 -> 1500000
B26: Couverture médiatique (transport des journaliste) | C26: 20 | D26: Journalistes | E26: 1 | F26: jour | G26: 5000 | H26: =C26*E26*G26 -> 100000
B27: Reportage photo-vidéo | C27: 2 | D27: reporter | E27: 1 | F27: jour | G27: 150000 | H27: =C27*E27*G27 -> 300000
A28: Sous-total 1.2. | B28: Organisation de la cérémonie de lancement du Youth Challenge | H28: =SUM(H24:H27) -> 2050000 | I28: =H28/I6 -> 3472.1046 | J28: 0 | K28: 0 | L28: =I28-J28-K28 -> 3472.1046
A29: TOTAL DE L’EXTRANT 1: Sensibilisation sur le projet | H29: =H21+H28 -> 4403000 | I29: =I21+I28 -> 7457.4032 | J29: =J21+J28 -> 1000 | K29: 0 | L29: =L21+L28 -> 6457.4032
A30: Extrant 2 | B30: Organisation des ateliers de conception ( Boootcamps)
A31: Activité 2.1 | B31: Préparation des ateliers
A32: Grp.Cibles | B32: Ministères, partenaires techniques et financiers éventuels participants
B33: Collation pendant le briefing du comite de présélection | C33: 10 | D33: Personne | E33: 1 | F33: réunion | G33: 3000 | H33: =C33*E33*G33 -> 30000
B34: collation pendant les réunions du comité de pre-selection sélection des offres | C34: 10 | D34: Personnes | E34: 2 | F34: Réunions | G34: 2000 | H34: =C34*E34*G34 -> 40000
B35: Constitution des kits pour les membres du comité ( feuilles, stylos, de notation, blocs notes etc.) | C35: 10 | D35: Personnes | E35: 1 | F35: Kit | G35: 1500 | H35: =C35*E35*G35 -> 15000
B36: Frais de transport pour les membres du comité de sélection | C36: 5 | D36: Personnes | E36: 2 | F36: réunion | G36: 5000 | H36: =C36*E36*G36 -> 50000
B37: Duplication des fiches d'inscription | C37: 1 | D37: fiche de 2 pages | E37: 200 | F37: copies | G37: 50 | H37: =C37*E37*G37 -> 10000
A38: Sous-total 2.1 | B38: Préparation des ateliers | H38: =SUM(H33:H37) -> 145000 | I38: =H38/I6 -> 245.58789 | J38: 0 | K38: =I38 -> 245.58789 | L38: =I38-J38-K38 -> 0
A39: Activité 2.2 | B39: organisation de l'atelier d'orientation
A40: Grp.Cibles | B40: candidats, coach, équipes, superviseurs, comite technique
B41: Kits de formation | C41: 50 | D41: personnes | E41: 1 | F41: Jour | G41: 2000 | H41: =G41*E41*C41 -> 100000
B42: collation pendant l'atelier d'orientation | C42: 60 | D42: Personnes | E42: 1 | F42: Jour | G42: 3000 | H42: =G42*E42*C42 -> 180000
B43: Déplacement des participants | C43: 50 | D43: Personnes | E43: 1 | F43: Jour | G43: 5000 | H43: =G43*E43*C43 -> 250000
B44: Logistique ateliers ( fournitures de bureaux, photocopie des documents, constitution des Kits etc.) | C44: 1 | D44: Forfait | E44: 1 | F44: fois | G44: 100000 | H44: =C44*E44*G44 -> 100000
B45: Frais de facilitation | C45: 3 | D45: Personnes | E45: 1 | F45: fois | G45: 25000 | H45: =C45*E45*G45 -> 75000
A46: Sous-total 2.2 | B46: Organisation de l'atelier d'orientation | H46: =SUM(H41:H45) -> 705000 | I46: =H46/I6 -> 1194.0652 | J46: 0 | K46: =I46-J46 -> 1194.0652 | L46: =I46-J46-K46 -> 0
A47: Activité 2.3 | B47: Organisation des ateliers résidentiels de conception( Bootcam)
B48: Hébergement et nutrition de participants et coachs | C48: 55 | D48: Personnes | E48: 3 | F48: nuitées | G48: 50000 | H48: =C48*E48*G48 -> 8250000
B49: Frais de déplacement des participants | C49: 55 | D49: Personnes | E49: 2 | F49: voyages | G49: 5000 | H49: =C49*E49*G49 -> 550000
A50: Sous-total 2.3: | B50: Organisation des ateliers résidentiels de conception( Bootcam) | H50: =SUM(H48:H49) -> 8800000 | I50: =H50/I6 -> 14904.644 | J50: 9000 | K50: =I50-J50 -> 5904.6442 | L50: =I50-J50-K50 -> 0
A51: TOTAL DE L’EXTRANT 2: Organisation des ateliers | H51: =H38+H46+H50 -> 9650000 | J51: =J39+J46+J50 -> 9000 | K51: =K38+K46+K50 -> 7344.2973 | L51: =L38+L46+L50 -> 0
A52: Extrant 3 | B52: Sélection des gagnants et soumission au niveau global
A53: Activité 3.1 | B53: Remise des prix aux gagnants
A54: Grp.Cibles | B54: Participants, partenaires de mise en œuvre
B55: Prix | C55: 1 | D55: Prix | E55: 5 | F55: groupes | G55: 590420 | H55: =G55*E55*C55 -> 2952100
A56: Sous-total: 3.1 | B56: Remise des prix aux gagnants | H56: =H55 -> 2952100 | I56: =H56/I6 -> 5000 | J56: =I56 -> 5000 | K56: 0 | L56: =I56-J56-K56 -> 0
A57: Activité 3.2 | B57: Organisation de la cérémonie de publication des résultats
A58: Grp.Cibles | B58: Grand public: Décideurs, ministres, partenaires techniques et financiers…
B59: Location de la salle | C59: 1 | E59: 1 | F59: Jour | G59: 100000 | H59: =C59*E59*G59 -> 100000
B60: Couverture médiatique | C60: 20 | D60: Journalistes | E60: 1 | F60: Jour | G60: 5000 | H60: =G60*E60*C60 -> 100000
B61: Collation | C61: 100 | D61: Personnes | E61: 1 | F61: Jour | G61: 3000 | H61: =G61*E61*C61 -> 300000
A62: Sous-total 3.2: | B62: Organisation de la cérémonie de publication des résultats | H62: =SUM(H59:H61) -> 500000 | I62: =H62/I6 -> 846.85478 | J62: 0 | K62: 847 | L62: 0
A63: Activités 3.3: Accompagnement des projets
A64: Grp.Cibles | B64: Participants, comité de sélection, partenaires techniques et financiers…
B65: Frais de supervision par les cadres des Ministères | C65: 2 | D65: Personnes | E65: 3 | F65: Mois | G65: 10000 | H65: =G65*E65*C65 -> 60000
B66: Frais de coaching | C66: 5 | D66: Personnes | E66: 3 | F66: Mois | G66: 50000 | H66: =G66*E66*C66 -> 750000
B67: Réunions techniques | C67: 3 | D67: Réunions | E67: 1 | F67: Forfait | G67: 50000 | H67: =G67*E67*C67 -> 150000
A68: Sous-total 3.3: | B68: Accompagnement des projets | H68: =SUM(H65:H67) -> 960000 | I68: =H68/I6 -> 1625.9612 | J68: 0 | K68: 0 | L68: =I68-J68-K68 -> 1625.9612
A69: TOTAL DE L’EXTRANT 3: Sélection des gagnants et soumission au niveau global | H69: =H56+H62+H68 -> 4412100 | I69: =H69/I6 -> 7472.816 | J69: =J56+J62+J68 -> 5000 | K69: =K56+K62+K68 -> 847 | L69: =L56+L62+L68 -> 1625.9612
A70: COUT TOTAL | H70: =H29+H51+H69 -> 18465100 | I70: =H70/I6 -> 31274.516 | J70: =J29+J51+J69 -> 15000 | K70: =K29+K51+K69 -> 8191.2973 | L70: =L29+L51+L69 -> 8083.3644
C73: SYNTHESE BUDGET
E75: Budget en FCFA | F75: Budget en USD | G75: Fonds GenU | H75: Apport UNDP | I75: Apport UNICEF
E76: =H70 -> 18465100 | F76: =I70 -> 31274.516 | G76: =J70 -> 15000 | H76: =K70 -> 8191.2973 | I76: =L70 -> 8083.3644
G78: Fait à Brazzaville, le
C81: Pour L'UNDP | G81: Pour l’UNICEF
C84: Emma Ngouan-Anoh | G84: Andrés. A. LOPEZ
C85: Deputy Representative | G85: Deputy Representative

Sheet Apport par structure
A4: Génération Sans Limites/ Youth Challenge 2019/2020
A5: Contributions des différentes parties prenantes par activité
A7: 1- Financement de Generation Unlimeted
A8: Activités | B8: Montant en USD
A9: Communication sur le projet (dépliants, gadgets, presse, etc.) | B9: ='Budget détaillé'!J21 -> 1000
A10: Organisation des ateliers résidentiels de conception( Bootcam) | B10: ='Budget détaillé'!J50 -> 9000
A11: Remise des prix aux gagnants | B11: ='Budget détaillé'!J56 -> 5000
A13: Total Financement GenU | B13: =B9+B10+B11 -> 15000
A15: 2- Apport UNDP
A16: Activités | B16: Montant en USD
A17: Préparation des ateliers | B17: ='Budget détaillé'!I38 -> 245.58789
A18: Organisation de l'atelier d'orientation | B18: ='Budget détaillé'!K46 -> 1194.0652
A19: Complément organisation des ateliers résidentiels de conception (Bootcam) | B19: ='Budget détaillé'!K50 -> 5904.6442
A20: Organisation de la cérémonie de publication des résultats | B20: ='Budget détaillé'!K62 -> 847
A21: Total Apport UNDP | B21: =SUM(B17:B20) -> 8191.2973
A23: 2- Apport UNICEF
A24: Activités | B24: Montant en USD
A25: Communication sur le projet (dépliants, gadgets, presse, etc.) | B25: ='Budget détaillé'!L21 -> 2985.2986
A26: Organisation de la cérémonie de lancement du Youth Challenge | B26: ='Budget détaillé'!L28 -> 3472.1046
A27: Accompagnement des projets | B27: ='Budget détaillé'!L68 -> 1625.9612
A28: Total Apport UNICEF | B28: =SUM(B25:B27) -> 8083.3644
